s3_deploy/__init__.py
s3_deploy/config.py
s3_deploy/deploy.py
s3_deploy/filematch.py
s3_deploy/prefixcovertree.py
s3_deploy/tests/__init__.py
s3_deploy/tests/test_config.py
s3_deploy/tests/test_deploy.py
s3_deploy/tests/test_filematch.py
s3_deploy/tests/test_prefixcovertree.py
s3_deploy_website-0.3.0.dist-info/LICENSE
s3_deploy_website-0.3.0.dist-info/METADATA
s3_deploy_website-0.3.0.dist-info/WHEEL
s3_deploy_website-0.3.0.dist-info/entry_points.txt
s3_deploy_website-0.3.0.dist-info/top_level.txt
s3_deploy_website-0.3.0.dist-info/RECORD
