Metadata-Version: 2.1
Name: s3-deploy-website
Version: 0.3.0
Summary: S3 website deployment tool
Home-page: UNKNOWN
Author: Jon Lund Steffensen
Author-email: jonlst@gmail.com
License: MIT
Platform: UNKNOWN
Classifier: Development Status :: 4 - Beta
Classifier: Intended Audience :: Developers
Classifier: License :: OSI Approved :: MIT License
Classifier: Programming Language :: Python :: 2.7
Classifier: Programming Language :: Python :: 3.4
Classifier: Programming Language :: Python :: 3.5
Classifier: Programming Language :: Python :: 3.6
Classifier: Programming Language :: Python :: 3.7
Classifier: Topic :: Internet :: WWW/HTTP :: Site Management
Requires-Dist: boto3 (<1.8,>=1.7)
Requires-Dist: PyYAML (~=3.11)
Requires-Dist: six (~=1.10)
